starlink/__init__.py
starlink/atools.py
starlink/ccdpack.py
starlink/convert.py
starlink/cupid.py
starlink/figaro.py
starlink/fluxes.py
starlink/hdsutils.py
starlink/kappa.py
starlink/picard.py
starlink/polpack.py
starlink/smurf.py
starlink/utilities.py
starlink/wrapper.py
starlink/atools_help/astaddframe.rst
starlink/atools_help/astaddvariant.rst
starlink/atools_help/astangle.rst
starlink/atools_help/astbox.rst
starlink/atools_help/astchebydomain.rst
starlink/atools_help/astchebymap.rst
starlink/atools_help/astcircle.rst
starlink/atools_help/astclear.rst
starlink/atools_help/astcmpframe.rst
starlink/atools_help/astcmpmap.rst
starlink/atools_help/astcmpregion.rst
starlink/atools_help/astconvert.rst
starlink/atools_help/astconvex.rst
starlink/atools_help/astcopy.rst
starlink/atools_help/astdistance.rst
starlink/atools_help/astdownsize.rst
starlink/atools_help/astdsbframe.rst
starlink/atools_help/astellipse.rst
starlink/atools_help/astfindframe.rst
starlink/atools_help/astfluxframe.rst
starlink/atools_help/astformat.rst
starlink/atools_help/astframe.rst
starlink/atools_help/astframeset.rst
starlink/atools_help/astfromhds.rst
starlink/atools_help/astget.rst
starlink/atools_help/astgetactunit.rst
starlink/atools_help/astgetframe.rst
starlink/atools_help/astgetmapping.rst
starlink/atools_help/astgetrefpos.rst
starlink/atools_help/astgetregbounds.rst
starlink/atools_help/astgetregframe.rst
starlink/atools_help/astgetunc.rst
starlink/atools_help/astinterval.rst
starlink/atools_help/astinvert.rst
starlink/atools_help/astlinearapprox.rst
starlink/atools_help/astlutmap.rst
starlink/atools_help/astmapbox.rst
starlink/atools_help/astmapregion.rst
starlink/atools_help/astmapsplit.rst
starlink/atools_help/astmask.rst
starlink/atools_help/astmatchaxes.rst
starlink/atools_help/astmathmap.rst
starlink/atools_help/astmatrixmap.rst
starlink/atools_help/astmirrorvars.rst
starlink/atools_help/astnegate.rst
starlink_pywrapper-0.3.dist-info/DESCRIPTION.rst
starlink_pywrapper-0.3.dist-info/METADATA
starlink_pywrapper-0.3.dist-info/RECORD
starlink_pywrapper-0.3.dist-info/WHEEL
starlink_pywrapper-0.3.dist-info/metadata.json
starlink_pywrapper-0.3.dist-info/top_level.txt
