Metadata-Version: 2.0
Name: starlink-pywrapper
Version: 0.3
Summary: Provides a wrapper around the Starlink software suite commands.
Home-page: http://github.com/Starlink/starlink-pywrapper
Author: SF Graves
Author-email: s.graves@eaobservatory.org
License: GPLv3+
Platform: UNKNOWN
Classifier: Topic :: Scientific/Engineering :: Astronomy
Classifier: License :: OSI Approved :: GNU General Public License v3 or later (GPLv3+)
Requires-Dist: starlink-pyhds
